{
  "package-id": "bd.fhir.core",
  "title": "Bangladesh Core FHIR Implementation Guide",
  "canonical": "https://fhir.dghs.gov.bd/core",
  "introduction": "The Bangladesh Core FHIR IG defines national base profiles, value sets, and extensions for health data interoperability.",
  "list": [
    {
      "version": "current",
      "desc": "Continuous Integration Build (latest in development)",
      "path": "https://fhir.dghs.gov.bd/core/",
      "status": "ci-build",
      "current": true
    },
    {
      "version": "0.4.1",
      "date": "2026-04-06",
      "desc": "DGDA Drug and LOINC Integration with minor bug fixes",
      "path": "https://fhir.dghs.gov.bd/core/0.4.1/",
      "status": "trial-use",
      "sequence": "STU 1"
    },
    {
      "version": "0.4.0",
      "date": "2026-04-06",
      "desc": "DGDA Drug and LOINC Integration",
      "path": "https://fhir.dghs.gov.bd/core/0.4.0/",
      "status": "trial-use",
      "sequence": "STU 1"
    },
    {
      "version": "0.3.0",
      "date": "2026-03-08",
      "desc": "ICD-11 MMS integration and minor bug fixes",
      "path": "https://fhir.dghs.gov.bd/core/0.3.0/",
      "status": "trial-use",
      "sequence": "STU 1"
    },
    {
      "version": "0.2.5",
      "date": "2025-10-06",
      "desc": "Minor bug fix release",
      "path": "https://fhir.dghs.gov.bd/core/0.2.5/",
      "status": "trial-use",
      "sequence": "STU 1"
    },
    {
      "version": "0.2.4",
      "date": "2025-10-06",
      "desc": "Minor visual improvements",
      "path": "https://fhir.dghs.gov.bd/core/0.2.4/",
      "status": "trial-use",
      "sequence": "STU 1"
    },
    {
      "version": "0.2.3",
      "date": "2025-10-06",
      "desc": "Minor documentation updates",
      "path": "https://fhir.dghs.gov.bd/core/0.2.3/",
      "status": "trial-use",
      "sequence": "STU 1"
    },
    {
      "version": "0.2.2",
      "date": "2025-10-06",
      "desc": "Minor bug fix release",
      "path": "https://fhir.dghs.gov.bd/core/0.2.2/",
      "status": "trial-use",
      "sequence": "STU 1"
    },
    {
      "version": "0.2.1",
      "date": "2025-10-06",
      "desc": "Second draft release of the Bangladesh Core FHIR IG",
      "path": "https://fhir.dghs.gov.bd/core/0.2.1/",
      "status": "trial-use",
      "sequence": "STU 1"
    },
    {
      "version": "0.2.0",
      "date": "2025-10-02",
      "desc": "First draft release of the Bangladesh Core FHIR IG",
      "path": "https://fhir.dghs.gov.bd/core/0.2.0/",
      "status": "trial-use",
      "sequence": "STU 1"
    }
  ]
}